sjournal/__init__.py
sjournal/sjournal.py
sjournal/utilities/__init__.py
sjournal/utilities/arguments.py
sjournal/utilities/utilities.py
sjournal/utilities/version.py
sjournal-0.2.2.dist-info/METADATA
sjournal-0.2.2.dist-info/WHEEL
sjournal-0.2.2.dist-info/entry_points.txt
sjournal-0.2.2.dist-info/top_level.txt
sjournal-0.2.2.dist-info/RECORD
