Metadata-Version: 2.1
Name: sjournal
Version: 0.2.2
Summary: A simple and light-weight notepad for the command line
Home-page: https://github.com/SamuelStuver/sjournal
Author: Sam Stuver
Author-email: samuelstuver@gmail.com
License: UNKNOWN
Platform: UNKNOWN
Classifier: License :: OSI Approved :: MIT License
Classifier: Operating System :: Microsoft :: Windows :: Windows 10
Classifier: Operating System :: POSIX :: Linux
Classifier: Programming Language :: Python :: 3.8
Classifier: Programming Language :: Python :: 3.9
Classifier: Programming Language :: Python :: 3.10
Requires-Dist: PySimpleGUI (>=4.57.0)
Requires-Dist: rich (>=12.0.0)
Requires-Dist: pyperclip (>=1.8.2)
Requires-Dist: setuptools (>=60.9.3)
